tidy_dict/__init__.py
tidy_dict-2.0.0.dist-info/LICENSE
tidy_dict-2.0.0.dist-info/METADATA
tidy_dict-2.0.0.dist-info/WHEEL
tidy_dict-2.0.0.dist-info/top_level.txt
tidy_dict-2.0.0.dist-info/RECORD
