Metadata-Version: 2.1
Name: tidy-dict
Version: 2.0.0
Summary: A tool for easy Nested Dictionaries with option to output tidy CSV files.
Home-page: https://github.com/atomoton/tidy_dict
Author: Andrew E Brereton
Author-email: andrew@brereton.me
License: UNKNOWN
Platform: UNKNOWN
Classifier: Programming Language :: Python :: 3
Classifier: License :: OSI Approved :: GNU General Public License v3 (GPLv3)
Classifier: Operating System :: OS Independent
